bitcodin/__init__.py
bitcodin/api.py
bitcodin/error.py
bitcodin/exceptions.py
bitcodin/resource.py
bitcodin/rest.py
bitcodin/util.py
bitcodin-1.6.9.dist-info/DESCRIPTION.rst
bitcodin-1.6.9.dist-info/METADATA
bitcodin-1.6.9.dist-info/RECORD
bitcodin-1.6.9.dist-info/WHEEL
bitcodin-1.6.9.dist-info/metadata.json
bitcodin-1.6.9.dist-info/top_level.txt
