Metadata-Version: 2.0
Name: bitcodin
Version: 1.6.9
Summary: Python interface for bitcodin API
Home-page: https://github.com/bitmovin/bitcodin-python
Author: David Moser, Dominic Miglar
Author-email: david.moser@bitmovin.net, dominic.miglar@bitmovin.net
License: UNKNOWN
Platform: UNKNOWN
Classifier: Development Status :: 4 - Beta
Classifier: Intended Audience :: Developers
Classifier: Programming Language :: Python :: 2.7
Classifier: Programming Language :: Python :: 3.4
Requires-Dist: requests (>=2.4.3)
